mend_project_cleanup_tool/__init__.py
mend_project_cleanup_tool/_version.py
mend_project_cleanup_tool/project_cleanup_tool.py
mend_project_cleanup_tool-25.12.3.dist-info/licenses/LICENSE
mend_project_cleanup_tool-25.12.3.dist-info/METADATA
mend_project_cleanup_tool-25.12.3.dist-info/WHEEL
mend_project_cleanup_tool-25.12.3.dist-info/entry_points.txt
mend_project_cleanup_tool-25.12.3.dist-info/top_level.txt
mend_project_cleanup_tool-25.12.3.dist-info/RECORD
