Metadata-Version: 2.4
Name: mend_project_cleanup_tool
Version: 25.12.3
Summary: Mend Cleanup Tool
Home-page: https://github.com/mend-toolkit/mend-project-cleanup-tool
Author: Mend Professional Services
Author-email: ps@whitesourcesoftware.com
License: LICENSE.txt
Classifier: Programming Language :: Python :: 3.9
Classifier: Programming Language :: Python :: 3.10
Classifier: Programming Language :: Python :: 3.11
Classifier: License :: OSI Approved :: Apache Software License
Classifier: Operating System :: OS Independent
Requires-Python: >=3.9
License-File: LICENSE
Requires-Dist: configparser==7.2.0
Requires-Dist: DateTime~=4.3
Requires-Dist: setuptools==78.1.1
Requires-Dist: requests~=2.32.5
Dynamic: author
Dynamic: author-email
Dynamic: classifier
Dynamic: description
Dynamic: description-content-type
Dynamic: home-page
Dynamic: license
Dynamic: license-file
Dynamic: requires-dist
Dynamic: requires-python
Dynamic: summary
